gui_scripter/__init__.py
gui_scripter/cli.py
gui_scripter/images.py
gui_scripter-1.0.4.dist-info/LICENSE
gui_scripter-1.0.4.dist-info/METADATA
gui_scripter-1.0.4.dist-info/WHEEL
gui_scripter-1.0.4.dist-info/entry_points.txt
gui_scripter-1.0.4.dist-info/top_level.txt
gui_scripter-1.0.4.dist-info/RECORD
