Metadata-Version: 2.1
Name: gui-scripter
Version: 1.0.4
Summary: Simple GUI for Python Scripts
Home-page: https://github.com/MayasMess/gui-scripter/issues
Author: Amayas Messara
Author-email: amayas.messara@gmail.com
License: UNKNOWN
Project-URL: Bug Tracker, https://github.com/MayasMess/pandas-oop/issues
Keywords: gui,scripts,simple gui,python gui
Platform: UNKNOWN
Classifier: Programming Language :: Python :: 3
Classifier: License :: OSI Approved :: MIT License
Classifier: Operating System :: OS Independent
Requires-Python: >=3.6
License-File: LICENSE
Requires-Dist: altgraph
Requires-Dist: macholib
Requires-Dist: Pillow
Requires-Dist: ttkthemes
